cleandoc/__init__.py
cleandoc/clean.py
cleandoc/cli.py
cleandoc/doq.py
cleandoc/helper.py
cleandoc/py.typed
cleandoc/sphinxdoc.py
cleandoc-0.0.14.dist-info/LICENSE.txt
cleandoc-0.0.14.dist-info/METADATA
cleandoc-0.0.14.dist-info/WHEEL
cleandoc-0.0.14.dist-info/entry_points.txt
cleandoc-0.0.14.dist-info/top_level.txt
cleandoc-0.0.14.dist-info/RECORD
