Metadata-Version: 2.1
Name: cleandoc
Version: 0.0.14
Author-email: Jason Krist <jkrist2696@gmail.com>
License: GPL-3.0-only
Project-URL: Homepage, https://github.com/jkrist2696/cleandoc
Classifier: Programming Language :: Python :: 3
Classifier: License :: OSI Approved :: GNU General Public License v3 (GPLv3)
Classifier: Operating System :: Microsoft :: Windows
Classifier: Operating System :: Unix
Requires-Python: >=3.6
License-File: LICENSE.txt
Requires-Dist: black >=23.3.0
Requires-Dist: Sphinx >=6.2.1
Requires-Dist: doq >=0.9.1
Requires-Dist: m2r2
Requires-Dist: sphinx-rtd-theme
Requires-Dist: pylint
Requires-Dist: mypy
